plexauth.py
plexauth-0.0.6.dist-info/LICENSE
plexauth-0.0.6.dist-info/METADATA
plexauth-0.0.6.dist-info/WHEEL
plexauth-0.0.6.dist-info/top_level.txt
plexauth-0.0.6.dist-info/RECORD
