Metadata-Version: 2.1
Name: plexauth
Version: 0.0.6
Summary: Handles the authorization flow to obtain tokens from Plex.tv via external redirection.
Home-page: https://github.com/jjlawren/python-plexauth/
Author: Jason Lawrence
Author-email: jjlawren@users.noreply.github.com
License: MIT
Platform: any
Classifier: License :: OSI Approved :: MIT License
Classifier: Operating System :: OS Independent
Classifier: Programming Language :: Python :: 3.5
Classifier: Programming Language :: Python :: 3.6
Classifier: Programming Language :: Python :: 3.7
